alphahousepython-1.0.6.dist-info/RECORD
alphahousepython-1.0.6.dist-info/METADATA
alphahousepython-1.0.6.dist-info/top_level.txt
alphahousepython-1.0.6.dist-info/WHEEL
alphahousepython/PyIntersectCompare.cpython-36m-x86_64-linux-gnu.so
alphahousepython/hap.cpython-36m-x86_64-linux-gnu.so
alphahousepython/Exceptions.cpython-36m-x86_64-linux-gnu.so
alphahousepython/haplib.cpython-36m-x86_64-linux-gnu.so
alphahousepython/__init__.py
alphahousepython/gen.cpython-36m-x86_64-linux-gnu.so
alphahousepython/ped.cpython-36m-x86_64-linux-gnu.so
alphahousepython/src/Constants.py
alphahousepython/src/HaplotypeLibrary.py
alphahousepython/src/Haplotype.py
alphahousepython/src/Utils.py
alphahousepython/src/PedigreeHolder.py
alphahousepython/src/Genotype.py
alphahousepython/src/__init__.py
alphahousepython/src/genotypesDiff.py
alphahousepython/src/_faker.py
alphahousepython/src/HeuristicGeneProb.py
